{
  "15.0.0": {
    "PropertyTypes": {
      "AWS::EC2::ClientVpnEndpoint.FederatedAuthenticationRequest": {
        "AllRegions": false,
        "Documentation": "http://docs.aws.amazon.com/AWSCloudFormation/latest/UserGuide/aws-properties-ec2-clientvpnendpoint-federatedauthenticationrequest.html",
        "Expanded": [
          "ap-south-1",
          "eu-north-1",
          "us-east-1",
          "ap-northeast-2",
          "ca-central-1",
          "us-west-1",
          "ap-southeast-1",
          "eu-west-2",
          "ap-northeast-1",
          "us-east-2",
          "eu-west-1",
          "eu-central-1"
        ],
        "Reduced": [],
        "Type": "Existing"
      },
      "AWS::EFS::AccessPoint.AccessPointTag": {
        "AllRegions": false,
        "Documentation": "http://docs.aws.amazon.com/AWSCloudFormation/latest/UserGuide/aws-properties-efs-accesspoint-accesspointtag.html",
        "Regions": [
          "ap-east-1",
          "ap-northeast-1",
          "ap-northeast-2",
          "ap-south-1",
          "ap-southeast-1",
          "ap-southeast-2",
          "ca-central-1",
          "cn-north-1",
          "cn-northwest-1",
          "eu-central-1",
          "eu-north-1",
          "eu-west-1",
          "eu-west-2",
          "eu-west-3",
          "me-south-1",
          "sa-east-1",
          "us-east-1",
          "us-east-2",
          "us-gov-east-1",
          "us-gov-west-1",
          "us-west-1",
          "us-west-2"
        ],
        "Type": "New"
      },
      "AWS::EFS::AccessPoint.CreationInfo": {
        "AllRegions": false,
        "Documentation": "http://docs.aws.amazon.com/AWSCloudFormation/latest/UserGuide/aws-properties-efs-accesspoint-creationinfo.html",
        "Regions": [
          "ap-east-1",
          "ap-northeast-1",
          "ap-northeast-2",
          "ap-south-1",
          "ap-southeast-1",
          "ap-southeast-2",
          "ca-central-1",
          "cn-north-1",
          "cn-northwest-1",
          "eu-central-1",
          "eu-north-1",
          "eu-west-1",
          "eu-west-2",
          "eu-west-3",
          "me-south-1",
          "sa-east-1",
          "us-east-1",
          "us-east-2",
          "us-gov-east-1",
          "us-gov-west-1",
          "us-west-1",
          "us-west-2"
        ],
        "Type": "New"
      },
      "AWS::EFS::AccessPoint.PosixUser": {
        "AllRegions": false,
        "Documentation": "http://docs.aws.amazon.com/AWSCloudFormation/latest/UserGuide/aws-properties-efs-accesspoint-posixuser.html",
        "Regions": [
          "ap-east-1",
          "ap-northeast-1",
          "ap-northeast-2",
          "ap-south-1",
          "ap-southeast-1",
          "ap-southeast-2",
          "ca-central-1",
          "cn-north-1",
          "cn-northwest-1",
          "eu-central-1",
          "eu-north-1",
          "eu-west-1",
          "eu-west-2",
          "eu-west-3",
          "me-south-1",
          "sa-east-1",
          "us-east-1",
          "us-east-2",
          "us-gov-east-1",
          "us-gov-west-1",
          "us-west-1",
          "us-west-2"
        ],
        "Type": "New"
      },
      "AWS::EFS::AccessPoint.RootDirectory": {
        "AllRegions": false,
        "Documentation": "http://docs.aws.amazon.com/AWSCloudFormation/latest/UserGuide/aws-properties-efs-accesspoint-rootdirectory.html",
        "Regions": [
          "ap-east-1",
          "ap-northeast-1",
          "ap-northeast-2",
          "ap-south-1",
          "ap-southeast-1",
          "ap-southeast-2",
          "ca-central-1",
          "cn-north-1",
          "cn-northwest-1",
          "eu-central-1",
          "eu-north-1",
          "eu-west-1",
          "eu-west-2",
          "eu-west-3",
          "me-south-1",
          "sa-east-1",
          "us-east-1",
          "us-east-2",
          "us-gov-east-1",
          "us-gov-west-1",
          "us-west-1",
          "us-west-2"
        ],
        "Type": "New"
      },
      "AWS::ImageBuilder::Image.Ami": {
        "AllRegions": false,
        "Documentation": "http://docs.aws.amazon.com/AWSCloudFormation/latest/UserGuide/aws-properties-imagebuilder-image-ami.html",
        "Regions": [
          "ap-east-1",
          "ap-northeast-1",
          "ap-northeast-2",
          "ap-south-1",
          "ap-southeast-1",
          "ap-southeast-2",
          "ca-central-1",
          "eu-central-1",
          "eu-north-1",
          "eu-west-1",
          "eu-west-2",
          "eu-west-3",
          "me-south-1",
          "sa-east-1",
          "us-east-1",
          "us-east-2",
          "us-gov-east-1",
          "us-gov-west-1",
          "us-west-1",
          "us-west-2"
        ],
        "Type": "New"
      },
      "AWS::ImageBuilder::Image.ImageState": {
        "AllRegions": false,
        "Documentation": "http://docs.aws.amazon.com/AWSCloudFormation/latest/UserGuide/aws-properties-imagebuilder-image-imagestate.html",
        "Regions": [
          "ap-east-1",
          "ap-northeast-1",
          "ap-northeast-2",
          "ap-south-1",
          "ap-southeast-1",
          "ap-southeast-2",
          "ca-central-1",
          "eu-central-1",
          "eu-north-1",
          "eu-west-1",
          "eu-west-2",
          "eu-west-3",
          "me-south-1",
          "sa-east-1",
          "us-east-1",
          "us-east-2",
          "us-gov-east-1",
          "us-gov-west-1",
          "us-west-1",
          "us-west-2"
        ],
        "Type": "New"
      },
      "AWS::ImageBuilder::Image.OutputResources": {
        "AllRegions": false,
        "Documentation": "http://docs.aws.amazon.com/AWSCloudFormation/latest/UserGuide/aws-properties-imagebuilder-image-outputresources.html",
        "Regions": [
          "ap-east-1",
          "ap-northeast-1",
          "ap-northeast-2",
          "ap-south-1",
          "ap-southeast-1",
          "ap-southeast-2",
          "ca-central-1",
          "eu-central-1",
          "eu-north-1",
          "eu-west-1",
          "eu-west-2",
          "eu-west-3",
          "me-south-1",
          "sa-east-1",
          "us-east-1",
          "us-east-2",
          "us-gov-east-1",
          "us-gov-west-1",
          "us-west-1",
          "us-west-2"
        ],
        "Type": "New"
      },
      "AWS::IoT::ProvisioningTemplate.ProvisioningHook": {
        "AllRegions": false,
        "Documentation": "http://docs.aws.amazon.com/AWSCloudFormation/latest/UserGuide/aws-properties-iot-provisioningtemplate-provisioninghook.html",
        "Regions": [
          "ap-east-1",
          "ap-northeast-1",
          "ap-northeast-2",
          "ap-south-1",
          "ap-southeast-1",
          "ap-southeast-2",
          "ca-central-1",
          "cn-north-1",
          "cn-northwest-1",
          "eu-central-1",
          "eu-north-1",
          "eu-west-1",
          "eu-west-2",
          "eu-west-3",
          "me-south-1",
          "sa-east-1",
          "us-east-1",
          "us-east-2",
          "us-gov-west-1",
          "us-west-1",
          "us-west-2"
        ],
        "Type": "New"
      },
      "AWS::KinesisFirehose::DeliveryStream.RedshiftRetryOptions": {
        "AllRegions": false,
        "Documentation": "http://docs.aws.amazon.com/AWSCloudFormation/latest/UserGuide/aws-properties-kinesisfirehose-deliverystream-redshiftretryoptions.html",
        "Expanded": [
          "ap-south-1",
          "us-gov-west-1",
          "eu-north-1",
          "us-east-1",
          "ap-northeast-2",
          "us-west-1",
          "ap-east-1",
          "us-east-2",
          "ap-northeast-1",
          "eu-west-3",
          "eu-west-2",
          "sa-east-1",
          "ap-southeast-2",
          "me-south-1",
          "ca-central-1",
          "cn-northwest-1",
          "ap-southeast-1",
          "us-west-2",
          "us-gov-east-1",
          "eu-west-1"
        ],
        "Reduced": [],
        "Type": "Existing"
      },
      "AWS::KinesisFirehose::DeliveryStream.VpcConfiguration": {
        "AllRegions": false,
        "Documentation": "http://docs.aws.amazon.com/AWSCloudFormation/latest/UserGuide/aws-properties-kinesisfirehose-deliverystream-vpcconfiguration.html",
        "Expanded": [
          "ap-south-1",
          "us-gov-west-1",
          "eu-north-1",
          "us-east-1",
          "ap-northeast-2",
          "us-west-1",
          "ap-east-1",
          "us-east-2",
          "ap-northeast-1",
          "eu-west-3",
          "eu-west-2",
          "sa-east-1",
          "ap-southeast-2",
          "me-south-1",
          "ca-central-1",
          "cn-northwest-1",
          "ap-southeast-1",
          "us-west-2",
          "us-gov-east-1",
          "eu-west-1"
        ],
        "Reduced": [],
        "Type": "Existing"
      },
      "AWS::RDS::DBProxy.AuthFormat": {
        "AllRegions": false,
        "Documentation": "http://docs.aws.amazon.com/AWSCloudFormation/latest/UserGuide/aws-properties-rds-dbproxy-authformat.html",
        "Regions": [
          "ap-northeast-1",
          "ap-northeast-2",
          "ap-south-1",
          "ap-southeast-1",
          "ap-southeast-2",
          "ca-central-1",
          "eu-central-1",
          "eu-west-1",
          "eu-west-2",
          "us-east-1",
          "us-east-2",
          "us-west-1",
          "us-west-2"
        ],
        "Type": "New"
      },
      "AWS::RDS::DBProxy.TagFormat": {
        "AllRegions": false,
        "Documentation": "http://docs.aws.amazon.com/AWSCloudFormation/latest/UserGuide/aws-properties-rds-dbproxy-tagformat.html",
        "Regions": [
          "ap-northeast-1",
          "ap-northeast-2",
          "ap-south-1",
          "ap-southeast-1",
          "ap-southeast-2",
          "ca-central-1",
          "eu-central-1",
          "eu-west-1",
          "eu-west-2",
          "us-east-1",
          "us-east-2",
          "us-west-1",
          "us-west-2"
        ],
        "Type": "New"
      },
      "AWS::RDS::DBProxyTargetGroup.ConnectionPoolConfigurationInfoFormat": {
        "AllRegions": false,
        "Documentation": "http://docs.aws.amazon.com/AWSCloudFormation/latest/UserGuide/aws-properties-rds-dbproxytargetgroup-connectionpoolconfigurationinfoformat.html",
        "Regions": [
          "ap-northeast-1",
          "ap-northeast-2",
          "ap-south-1",
          "ap-southeast-1",
          "ap-southeast-2",
          "ca-central-1",
          "eu-central-1",
          "eu-west-1",
          "eu-west-2",
          "us-east-1",
          "us-east-2",
          "us-west-1",
          "us-west-2"
        ],
        "Type": "New"
      }
    },
    "ResourceSpecificationVersionOld": "14.4.0",
    "ResourceTypes": {
      "AWS::EFS::AccessPoint": {
        "AllRegions": false,
        "Documentation": "http://docs.aws.amazon.com/AWSCloudFormation/latest/UserGuide/aws-resource-efs-accesspoint.html",
        "Regions": [
          "ap-east-1",
          "ap-northeast-1",
          "ap-northeast-2",
          "ap-south-1",
          "ap-southeast-1",
          "ap-southeast-2",
          "ca-central-1",
          "cn-north-1",
          "cn-northwest-1",
          "eu-central-1",
          "eu-north-1",
          "eu-west-1",
          "eu-west-2",
          "eu-west-3",
          "me-south-1",
          "sa-east-1",
          "us-east-1",
          "us-east-2",
          "us-gov-east-1",
          "us-gov-west-1",
          "us-west-1",
          "us-west-2"
        ],
        "Type": "New"
      },
      "AWS::IoT::ProvisioningTemplate": {
        "AllRegions": false,
        "Documentation": "http://docs.aws.amazon.com/AWSCloudFormation/latest/UserGuide/aws-resource-iot-provisioningtemplate.html",
        "Regions": [
          "ap-east-1",
          "ap-northeast-1",
          "ap-northeast-2",
          "ap-south-1",
          "ap-southeast-1",
          "ap-southeast-2",
          "ca-central-1",
          "cn-north-1",
          "cn-northwest-1",
          "eu-central-1",
          "eu-north-1",
          "eu-west-1",
          "eu-west-2",
          "eu-west-3",
          "me-south-1",
          "sa-east-1",
          "us-east-1",
          "us-east-2",
          "us-gov-west-1",
          "us-west-1",
          "us-west-2"
        ],
        "Type": "New"
      },
      "AWS::RDS::DBProxy": {
        "AllRegions": false,
        "Documentation": "http://docs.aws.amazon.com/AWSCloudFormation/latest/UserGuide/aws-resource-rds-dbproxy.html",
        "Regions": [
          "ap-northeast-1",
          "ap-northeast-2",
          "ap-south-1",
          "ap-southeast-1",
          "ap-southeast-2",
          "ca-central-1",
          "eu-central-1",
          "eu-west-1",
          "eu-west-2",
          "us-east-1",
          "us-east-2",
          "us-west-1",
          "us-west-2"
        ],
        "Type": "New"
      },
      "AWS::RDS::DBProxyTargetGroup": {
        "AllRegions": false,
        "Documentation": "http://docs.aws.amazon.com/AWSCloudFormation/latest/UserGuide/aws-resource-rds-dbproxytargetgroup.html",
        "Regions": [
          "ap-northeast-1",
          "ap-northeast-2",
          "ap-south-1",
          "ap-southeast-1",
          "ap-southeast-2",
          "ca-central-1",
          "eu-central-1",
          "eu-west-1",
          "eu-west-2",
          "us-east-1",
          "us-east-2",
          "us-west-1",
          "us-west-2"
        ],
        "Type": "New"
      }
    },
    "Totals": {
      "TotalPropertyTypes": {
        "Change": [
          11
        ],
        "Value": 1368
      },
      "TotalPropertyTypesSupportedGlobally": {
        "Change": [
          0
        ],
        "Value": 481
      },
      "TotalResourceTypes": {
        "Change": [
          4
        ],
        "Value": 542
      },
      "TotalResourceTypesSupportedGlobally": {
        "Change": [
          0
        ],
        "Value": 187
      }
    },
    "TypesNotInUSEAST1": {
      "PropertyTypes": {
        "AWS::ECS::Cluster.ClusterSetting": {
          "Documentation": "http://docs.aws.amazon.com/AWSCloudFormation/latest/UserGuide/aws-properties-ecs-cluster-clustersetting.html",
          "Fixed": false,
          "Regions": [
            "af-south-1",
            "ap-northeast-3",
            "eu-south-1"
          ],
          "Since": "14.4.0"
        },
        "AWS::GroundStation::DataflowEndpointGroup.DataflowEndpoint": {
          "Documentation": "http://docs.aws.amazon.com/AWSCloudFormation/latest/UserGuide/aws-properties-groundstation-dataflowendpointgroup-dataflowendpoint.html",
          "Fixed": false,
          "Regions": [
            "ap-southeast-2",
            "eu-north-1",
            "eu-west-1",
            "me-south-1",
            "us-east-2",
            "us-west-2"
          ],
          "Since": "14.4.0"
        },
        "AWS::GroundStation::DataflowEndpointGroup.EndpointDetails": {
          "Documentation": "http://docs.aws.amazon.com/AWSCloudFormation/latest/UserGuide/aws-properties-groundstation-dataflowendpointgroup-endpointdetails.html",
          "Fixed": false,
          "Regions": [
            "ap-southeast-2",
            "eu-north-1",
            "eu-west-1",
            "me-south-1",
            "us-east-2",
            "us-west-2"
          ],
          "Since": "14.4.0"
        },
        "AWS::GroundStation::DataflowEndpointGroup.SecurityDetails": {
          "Documentation": "http://docs.aws.amazon.com/AWSCloudFormation/latest/UserGuide/aws-properties-groundstation-dataflowendpointgroup-securitydetails.html",
          "Fixed": false,
          "Regions": [
            "ap-southeast-2",
            "eu-north-1",
            "eu-west-1",
            "me-south-1",
            "us-east-2",
            "us-west-2"
          ],
          "Since": "14.4.0"
        },
        "AWS::GroundStation::DataflowEndpointGroup.SocketAddress": {
          "Documentation": "http://docs.aws.amazon.com/AWSCloudFormation/latest/UserGuide/aws-properties-groundstation-dataflowendpointgroup-socketaddress.html",
          "Fixed": false,
          "Regions": [
            "ap-southeast-2",
            "eu-north-1",
            "eu-west-1",
            "me-south-1",
            "us-east-2",
            "us-west-2"
          ],
          "Since": "14.4.0"
        },
        "AWS::GroundStation::MissionProfile.DataflowEdge": {
          "Documentation": "http://docs.aws.amazon.com/AWSCloudFormation/latest/UserGuide/aws-properties-groundstation-missionprofile-dataflowedge.html",
          "Fixed": false,
          "Regions": [
            "ap-southeast-2",
            "eu-north-1",
            "eu-west-1",
            "me-south-1",
            "us-east-2",
            "us-west-2"
          ],
          "Since": "14.4.0"
        },
        "AWS::SSM::Association.ParameterValues": {
          "Documentation": "http://docs.aws.amazon.com/AWSCloudFormation/latest/UserGuide/aws-properties-ssm-association-parametervalues.html",
          "Fixed": false,
          "Regions": [
            "af-south-1",
            "ap-northeast-3",
            "eu-south-1"
          ],
          "Since": "14.4.0"
        }
      },
      "ResourceTypes": {
        "AWS::GroundStation::Config": {
          "Documentation": "http://docs.aws.amazon.com/AWSCloudFormation/latest/UserGuide/aws-resource-groundstation-config.html",
          "Fixed": false,
          "Regions": [
            "ap-southeast-2",
            "eu-north-1",
            "eu-west-1",
            "me-south-1",
            "us-east-2",
            "us-west-2"
          ],
          "Since": "14.4.0"
        },
        "AWS::GroundStation::DataflowEndpointGroup": {
          "Documentation": "http://docs.aws.amazon.com/AWSCloudFormation/latest/UserGuide/aws-resource-groundstation-dataflowendpointgroup.html",
          "Fixed": false,
          "Regions": [
            "ap-southeast-2",
            "eu-north-1",
            "eu-west-1",
            "me-south-1",
            "us-east-2",
            "us-west-2"
          ],
          "Since": "14.4.0"
        },
        "AWS::GroundStation::MissionProfile": {
          "Documentation": "http://docs.aws.amazon.com/AWSCloudFormation/latest/UserGuide/aws-resource-groundstation-missionprofile.html",
          "Fixed": false,
          "Regions": [
            "ap-southeast-2",
            "eu-north-1",
            "eu-west-1",
            "me-south-1",
            "us-east-2",
            "us-west-2"
          ],
          "Since": "14.4.0"
        }
      },
      "Total": {
        "Change": [
          0,
          3
        ],
        "Value": 10
      }
    }
  },
  "15.1.0": {
    "PropertyTypes": {
      "AWS::EC2::PrefixList.Entry": {
        "AllRegions": false,
        "Documentation": "http://docs.aws.amazon.com/AWSCloudFormation/latest/UserGuide/aws-properties-ec2-prefixlist-entry.html",
        "Regions": [
          "ap-northeast-1",
          "ap-southeast-1",
          "eu-central-1",
          "us-east-1",
          "us-west-2"
        ],
        "Type": "New"
      },
      "AWS::ECS::TaskDefinition.Options": {
        "AllRegions": false,
        "Documentation": "http://docs.aws.amazon.com/AWSCloudFormation/latest/UserGuide/aws-properties-ecs-taskdefinition-options.html",
        "Regions": [
          "eu-central-1"
        ],
        "Type": "New"
      },
      "AWS::Events::Rule.HttpParameters": {
        "AllRegions": true,
        "Documentation": "http://docs.aws.amazon.com/AWSCloudFormation/latest/UserGuide/aws-properties-events-rule-httpparameters.html",
        "Regions": [
          "af-south-1",
          "ap-east-1",
          "ap-northeast-1",
          "ap-northeast-2",
          "ap-northeast-3",
          "ap-south-1",
          "ap-southeast-1",
          "ap-southeast-2",
          "ca-central-1",
          "cn-north-1",
          "cn-northwest-1",
          "eu-central-1",
          "eu-north-1",
          "eu-south-1",
          "eu-west-1",
          "eu-west-2",
          "eu-west-3",
          "me-south-1",
          "sa-east-1",
          "us-east-1",
          "us-east-2",
          "us-gov-east-1",
          "us-gov-west-1",
          "us-west-1",
          "us-west-2"
        ],
        "Type": "New"
      },
      "AWS::ImageBuilder::Image.Ami": {
        "AllRegions": false,
        "Documentation": "http://docs.aws.amazon.com/AWSCloudFormation/latest/UserGuide/aws-properties-imagebuilder-image-ami.html",
        "Expanded": [],
        "Reduced": [
          "eu-west-1",
          "eu-west-3",
          "ap-northeast-2",
          "ca-central-1",
          "sa-east-1",
          "us-west-2",
          "eu-west-2",
          "eu-central-1",
          "us-west-1",
          "ap-northeast-1",
          "ap-southeast-1",
          "eu-north-1",
          "ap-south-1",
          "me-south-1",
          "us-gov-east-1",
          "ap-southeast-2",
          "us-east-2",
          "us-gov-west-1",
          "us-east-1"
        ],
        "Type": "Existing"
      },
      "AWS::ImageBuilder::Image.ImageState": {
        "AllRegions": false,
        "Documentation": "http://docs.aws.amazon.com/AWSCloudFormation/latest/UserGuide/aws-properties-imagebuilder-image-imagestate.html",
        "Expanded": [],
        "Reduced": [
          "eu-west-1",
          "eu-west-3",
          "ap-northeast-2",
          "ca-central-1",
          "sa-east-1",
          "us-west-2",
          "eu-west-2",
          "eu-central-1",
          "us-west-1",
          "ap-northeast-1",
          "ap-southeast-1",
          "eu-north-1",
          "ap-south-1",
          "me-south-1",
          "us-gov-east-1",
          "ap-southeast-2",
          "us-east-2",
          "us-gov-west-1",
          "us-east-1"
        ],
        "Type": "Existing"
      },
      "AWS::ImageBuilder::Image.OutputResources": {
        "AllRegions": false,
        "Documentation": "http://docs.aws.amazon.com/AWSCloudFormation/latest/UserGuide/aws-properties-imagebuilder-image-outputresources.html",
        "Expanded": [],
        "Reduced": [
          "eu-west-1",
          "eu-west-3",
          "ap-northeast-2",
          "ca-central-1",
          "sa-east-1",
          "us-west-2",
          "eu-west-2",
          "eu-central-1",
          "us-west-1",
          "ap-northeast-1",
          "ap-southeast-1",
          "eu-north-1",
          "ap-south-1",
          "me-south-1",
          "us-gov-east-1",
          "ap-southeast-2",
          "us-east-2",
          "us-gov-west-1",
          "us-east-1"
        ],
        "Type": "Existing"
      },
      "AWS::S3::Bucket.DeleteMarkerReplication": {
        "AllRegions": true,
        "Documentation": "http://docs.aws.amazon.com/AWSCloudFormation/latest/UserGuide/aws-properties-s3-bucket-deletemarkerreplication.html",
        "Regions": [
          "af-south-1",
          "ap-east-1",
          "ap-northeast-1",
          "ap-northeast-2",
          "ap-northeast-3",
          "ap-south-1",
          "ap-southeast-1",
          "ap-southeast-2",
          "ca-central-1",
          "cn-north-1",
          "cn-northwest-1",
          "eu-central-1",
          "eu-north-1",
          "eu-south-1",
          "eu-west-1",
          "eu-west-2",
          "eu-west-3",
          "me-south-1",
          "sa-east-1",
          "us-east-1",
          "us-east-2",
          "us-gov-east-1",
          "us-gov-west-1",
          "us-west-1",
          "us-west-2"
        ],
        "Type": "New"
      },
      "AWS::S3::Bucket.Metrics": {
        "AllRegions": true,
        "Documentation": "http://docs.aws.amazon.com/AWSCloudFormation/latest/UserGuide/aws-properties-s3-bucket-metrics.html",
        "Regions": [
          "af-south-1",
          "ap-east-1",
          "ap-northeast-1",
          "ap-northeast-2",
          "ap-northeast-3",
          "ap-south-1",
          "ap-southeast-1",
          "ap-southeast-2",
          "ca-central-1",
          "cn-north-1",
          "cn-northwest-1",
          "eu-central-1",
          "eu-north-1",
          "eu-south-1",
          "eu-west-1",
          "eu-west-2",
          "eu-west-3",
          "me-south-1",
          "sa-east-1",
          "us-east-1",
          "us-east-2",
          "us-gov-east-1",
          "us-gov-west-1",
          "us-west-1",
          "us-west-2"
        ],
        "Type": "New"
      },
      "AWS::S3::Bucket.ReplicationRuleAndOperator": {
        "AllRegions": true,
        "Documentation": "http://docs.aws.amazon.com/AWSCloudFormation/latest/UserGuide/aws-properties-s3-bucket-replicationruleandoperator.html",
        "Regions": [
          "af-south-1",
          "ap-east-1",
          "ap-northeast-1",
          "ap-northeast-2",
          "ap-northeast-3",
          "ap-south-1",
          "ap-southeast-1",
          "ap-southeast-2",
          "ca-central-1",
          "cn-north-1",
          "cn-northwest-1",
          "eu-central-1",
          "eu-north-1",
          "eu-south-1",
          "eu-west-1",
          "eu-west-2",
          "eu-west-3",
          "me-south-1",
          "sa-east-1",
          "us-east-1",
          "us-east-2",
          "us-gov-east-1",
          "us-gov-west-1",
          "us-west-1",
          "us-west-2"
        ],
        "Type": "New"
      },
      "AWS::S3::Bucket.ReplicationRuleFilter": {
        "AllRegions": true,
        "Documentation": "http://docs.aws.amazon.com/AWSCloudFormation/latest/UserGuide/aws-properties-s3-bucket-replicationrulefilter.html",
        "Regions": [
          "af-south-1",
          "ap-east-1",
          "ap-northeast-1",
          "ap-northeast-2",
          "ap-northeast-3",
          "ap-south-1",
          "ap-southeast-1",
          "ap-southeast-2",
          "ca-central-1",
          "cn-north-1",
          "cn-northwest-1",
          "eu-central-1",
          "eu-north-1",
          "eu-south-1",
          "eu-west-1",
          "eu-west-2",
          "eu-west-3",
          "me-south-1",
          "sa-east-1",
          "us-east-1",
          "us-east-2",
          "us-gov-east-1",
          "us-gov-west-1",
          "us-west-1",
          "us-west-2"
        ],
        "Type": "New"
      },
      "AWS::S3::Bucket.ReplicationTime": {
        "AllRegions": true,
        "Documentation": "http://docs.aws.amazon.com/AWSCloudFormation/latest/UserGuide/aws-properties-s3-bucket-replicationtime.html",
        "Regions": [
          "af-south-1",
          "ap-east-1",
          "ap-northeast-1",
          "ap-northeast-2",
          "ap-northeast-3",
          "ap-south-1",
          "ap-southeast-1",
          "ap-southeast-2",
          "ca-central-1",
          "cn-north-1",
          "cn-northwest-1",
          "eu-central-1",
          "eu-north-1",
          "eu-south-1",
          "eu-west-1",
          "eu-west-2",
          "eu-west-3",
          "me-south-1",
          "sa-east-1",
          "us-east-1",
          "us-east-2",
          "us-gov-east-1",
          "us-gov-west-1",
          "us-west-1",
          "us-west-2"
        ],
        "Type": "New"
      },
      "AWS::S3::Bucket.ReplicationTimeValue": {
        "AllRegions": true,
        "Documentation": "http://docs.aws.amazon.com/AWSCloudFormation/latest/UserGuide/aws-properties-s3-bucket-replicationtimevalue.html",
        "Regions": [
          "af-south-1",
          "ap-east-1",
          "ap-northeast-1",
          "ap-northeast-2",
          "ap-northeast-3",
          "ap-south-1",
          "ap-southeast-1",
          "ap-southeast-2",
          "ca-central-1",
          "cn-north-1",
          "cn-northwest-1",
          "eu-central-1",
          "eu-north-1",
          "eu-south-1",
          "eu-west-1",
          "eu-west-2",
          "eu-west-3",
          "me-south-1",
          "sa-east-1",
          "us-east-1",
          "us-east-2",
          "us-gov-east-1",
          "us-gov-west-1",
          "us-west-1",
          "us-west-2"
        ],
        "Type": "New"
      }
    },
    "ResourceSpecificationVersionOld": "15.0.0",
    "ResourceTypes": {
      "AWS::ApiGateway::VpcLink": {
        "AllRegions": false,
        "Documentation": "http://docs.aws.amazon.com/AWSCloudFormation/latest/UserGuide/aws-resource-apigateway-vpclink.html",
        "Expanded": [
          "af-south-1",
          "eu-south-1"
        ],
        "Reduced": [],
        "Type": "Existing"
      },
      "AWS::EC2::PrefixList": {
        "AllRegions": false,
        "Documentation": "http://docs.aws.amazon.com/AWSCloudFormation/latest/UserGuide/aws-resource-ec2-prefixlist.html",
        "Regions": [
          "ap-northeast-1",
          "ap-southeast-1",
          "eu-central-1",
          "us-east-1",
          "us-west-2"
        ],
        "Type": "New"
      }
    },
    "Totals": {
      "TotalPropertyTypes": {
        "Change": [
          9
        ],
        "Value": 1377
      },
      "TotalPropertyTypesSupportedGlobally": {
        "Change": [
          7
        ],
        "Value": 488
      },
      "TotalResourceTypes": {
        "Change": [
          1
        ],
        "Value": 543
      },
      "TotalResourceTypesSupportedGlobally": {
        "Change": [
          0
        ],
        "Value": 187
      }
    },
    "TypesNotInUSEAST1": {
      "PropertyTypes": {
        "AWS::ECS::Cluster.ClusterSetting": {
          "Documentation": "http://docs.aws.amazon.com/AWSCloudFormation/latest/UserGuide/aws-properties-ecs-cluster-clustersetting.html",
          "Fixed": false,
          "Regions": [
            "af-south-1",
            "ap-northeast-3",
            "eu-south-1"
          ],
          "Since": "15.0.0"
        },
        "AWS::ECS::TaskDefinition.Options": {
          "Documentation": "http://docs.aws.amazon.com/AWSCloudFormation/latest/UserGuide/aws-properties-ecs-taskdefinition-options.html",
          "Fixed": false,
          "Regions": [
            "eu-central-1"
          ],
          "Since": "15.1.0"
        },
        "AWS::GroundStation::DataflowEndpointGroup.DataflowEndpoint": {
          "Documentation": "http://docs.aws.amazon.com/AWSCloudFormation/latest/UserGuide/aws-properties-groundstation-dataflowendpointgroup-dataflowendpoint.html",
          "Fixed": false,
          "Regions": [
            "ap-southeast-2",
            "eu-north-1",
            "eu-west-1",
            "me-south-1",
            "us-east-2",
            "us-west-2"
          ],
          "Since": "15.0.0"
        },
        "AWS::GroundStation::DataflowEndpointGroup.EndpointDetails": {
          "Documentation": "http://docs.aws.amazon.com/AWSCloudFormation/latest/UserGuide/aws-properties-groundstation-dataflowendpointgroup-endpointdetails.html",
          "Fixed": false,
          "Regions": [
            "ap-southeast-2",
            "eu-north-1",
            "eu-west-1",
            "me-south-1",
            "us-east-2",
            "us-west-2"
          ],
          "Since": "15.0.0"
        },
        "AWS::GroundStation::DataflowEndpointGroup.SecurityDetails": {
          "Documentation": "http://docs.aws.amazon.com/AWSCloudFormation/latest/UserGuide/aws-properties-groundstation-dataflowendpointgroup-securitydetails.html",
          "Fixed": false,
          "Regions": [
            "ap-southeast-2",
            "eu-north-1",
            "eu-west-1",
            "me-south-1",
            "us-east-2",
            "us-west-2"
          ],
          "Since": "15.0.0"
        },
        "AWS::GroundStation::DataflowEndpointGroup.SocketAddress": {
          "Documentation": "http://docs.aws.amazon.com/AWSCloudFormation/latest/UserGuide/aws-properties-groundstation-dataflowendpointgroup-socketaddress.html",
          "Fixed": false,
          "Regions": [
            "ap-southeast-2",
            "eu-north-1",
            "eu-west-1",
            "me-south-1",
            "us-east-2",
            "us-west-2"
          ],
          "Since": "15.0.0"
        },
        "AWS::GroundStation::MissionProfile.DataflowEdge": {
          "Documentation": "http://docs.aws.amazon.com/AWSCloudFormation/latest/UserGuide/aws-properties-groundstation-missionprofile-dataflowedge.html",
          "Fixed": false,
          "Regions": [
            "ap-southeast-2",
            "eu-north-1",
            "eu-west-1",
            "me-south-1",
            "us-east-2",
            "us-west-2"
          ],
          "Since": "15.0.0"
        },
        "AWS::ImageBuilder::Image.Ami": {
          "Documentation": "http://docs.aws.amazon.com/AWSCloudFormation/latest/UserGuide/aws-properties-imagebuilder-image-ami.html",
          "Fixed": false,
          "Regions": [
            "ap-east-1"
          ],
          "Since": "15.0.0"
        },
        "AWS::ImageBuilder::Image.ImageState": {
          "Documentation": "http://docs.aws.amazon.com/AWSCloudFormation/latest/UserGuide/aws-properties-imagebuilder-image-imagestate.html",
          "Fixed": false,
          "Regions": [
            "ap-east-1"
          ],
          "Since": "15.0.0"
        },
        "AWS::ImageBuilder::Image.OutputResources": {
          "Documentation": "http://docs.aws.amazon.com/AWSCloudFormation/latest/UserGuide/aws-properties-imagebuilder-image-outputresources.html",
          "Fixed": false,
          "Regions": [
            "ap-east-1"
          ],
          "Since": "15.0.0"
        },
        "AWS::SSM::Association.ParameterValues": {
          "Documentation": "http://docs.aws.amazon.com/AWSCloudFormation/latest/UserGuide/aws-properties-ssm-association-parametervalues.html",
          "Fixed": false,
          "Regions": [
            "af-south-1",
            "ap-northeast-3",
            "eu-south-1"
          ],
          "Since": "15.0.0"
        }
      },
      "ResourceTypes": {
        "AWS::GroundStation::Config": {
          "Documentation": "http://docs.aws.amazon.com/AWSCloudFormation/latest/UserGuide/aws-resource-groundstation-config.html",
          "Fixed": false,
          "Regions": [
            "ap-southeast-2",
            "eu-north-1",
            "eu-west-1",
            "me-south-1",
            "us-east-2",
            "us-west-2"
          ],
          "Since": "15.0.0"
        },
        "AWS::GroundStation::DataflowEndpointGroup": {
          "Documentation": "http://docs.aws.amazon.com/AWSCloudFormation/latest/UserGuide/aws-resource-groundstation-dataflowendpointgroup.html",
          "Fixed": false,
          "Regions": [
            "ap-southeast-2",
            "eu-north-1",
            "eu-west-1",
            "me-south-1",
            "us-east-2",
            "us-west-2"
          ],
          "Since": "15.0.0"
        },
        "AWS::GroundStation::MissionProfile": {
          "Documentation": "http://docs.aws.amazon.com/AWSCloudFormation/latest/UserGuide/aws-resource-groundstation-missionprofile.html",
          "Fixed": false,
          "Regions": [
            "ap-southeast-2",
            "eu-north-1",
            "eu-west-1",
            "me-south-1",
            "us-east-2",
            "us-west-2"
          ],
          "Since": "15.0.0"
        }
      },
      "Total": {
        "Change": [
          1,
          0
        ],
        "Value": 14
      }
    }
  },
  "15.2.0": {
    "PropertyTypes": {
      "AWS::EC2::PrefixList.Entry": {
        "Documentation": "http://docs.aws.amazon.com/AWSCloudFormation/latest/UserGuide/aws-properties-ec2-prefixlist-entry.html",
        "Regions": [
          "ap-northeast-1",
          "ap-southeast-1",
          "eu-central-1",
          "us-east-1",
          "us-west-2"
        ],
        "Type": "Deleted"
      },
      "AWS::ECS::TaskDefinition.Options": {
        "Documentation": "http://docs.aws.amazon.com/AWSCloudFormation/latest/UserGuide/aws-properties-ecs-taskdefinition-options.html",
        "Regions": [
          "eu-central-1"
        ],
        "Type": "Deleted"
      },
      "AWS::ImageBuilder::Image.Ami": {
        "Documentation": "http://docs.aws.amazon.com/AWSCloudFormation/latest/UserGuide/aws-properties-imagebuilder-image-ami.html",
        "Regions": [
          "ap-east-1"
        ],
        "Type": "Deleted"
      },
      "AWS::ImageBuilder::Image.ImageState": {
        "Documentation": "http://docs.aws.amazon.com/AWSCloudFormation/latest/UserGuide/aws-properties-imagebuilder-image-imagestate.html",
        "Regions": [
          "ap-east-1"
        ],
        "Type": "Deleted"
      },
      "AWS::ImageBuilder::Image.OutputResources": {
        "Documentation": "http://docs.aws.amazon.com/AWSCloudFormation/latest/UserGuide/aws-properties-imagebuilder-image-outputresources.html",
        "Regions": [
          "ap-east-1"
        ],
        "Type": "Deleted"
      }
    },
    "ResourceSpecificationVersionOld": "15.1.0",
    "ResourceTypes": {
      "AWS::EC2::PrefixList": {
        "Documentation": "http://docs.aws.amazon.com/AWSCloudFormation/latest/UserGuide/aws-resource-ec2-prefixlist.html",
        "Regions": [
          "ap-northeast-1",
          "ap-southeast-1",
          "eu-central-1",
          "us-east-1",
          "us-west-2"
        ],
        "Type": "Deleted"
      }
    },
    "Totals": {
      "TotalPropertyTypes": {
        "Change": [
          -5
        ],
        "Value": 1372
      },
      "TotalPropertyTypesSupportedGlobally": {
        "Change": [
          0
        ],
        "Value": 488
      },
      "TotalResourceTypes": {
        "Change": [
          -1
        ],
        "Value": 542
      },
      "TotalResourceTypesSupportedGlobally": {
        "Change": [
          0
        ],
        "Value": 187
      }
    },
    "TypesNotInUSEAST1": {
      "PropertyTypes": {
        "AWS::ECS::Cluster.ClusterSetting": {
          "Documentation": "http://docs.aws.amazon.com/AWSCloudFormation/latest/UserGuide/aws-properties-ecs-cluster-clustersetting.html",
          "Fixed": false,
          "Regions": [
            "af-south-1",
            "ap-northeast-3",
            "eu-south-1"
          ],
          "Since": "15.1.0"
        },
        "AWS::GroundStation::DataflowEndpointGroup.DataflowEndpoint": {
          "Documentation": "http://docs.aws.amazon.com/AWSCloudFormation/latest/UserGuide/aws-properties-groundstation-dataflowendpointgroup-dataflowendpoint.html",
          "Fixed": false,
          "Regions": [
            "ap-southeast-2",
            "eu-north-1",
            "eu-west-1",
            "me-south-1",
            "us-east-2",
            "us-west-2"
          ],
          "Since": "15.1.0"
        },
        "AWS::GroundStation::DataflowEndpointGroup.EndpointDetails": {
          "Documentation": "http://docs.aws.amazon.com/AWSCloudFormation/latest/UserGuide/aws-properties-groundstation-dataflowendpointgroup-endpointdetails.html",
          "Fixed": false,
          "Regions": [
            "ap-southeast-2",
            "eu-north-1",
            "eu-west-1",
            "me-south-1",
            "us-east-2",
            "us-west-2"
          ],
          "Since": "15.1.0"
        },
        "AWS::GroundStation::DataflowEndpointGroup.SecurityDetails": {
          "Documentation": "http://docs.aws.amazon.com/AWSCloudFormation/latest/UserGuide/aws-properties-groundstation-dataflowendpointgroup-securitydetails.html",
          "Fixed": false,
          "Regions": [
            "ap-southeast-2",
            "eu-north-1",
            "eu-west-1",
            "me-south-1",
            "us-east-2",
            "us-west-2"
          ],
          "Since": "15.1.0"
        },
        "AWS::GroundStation::DataflowEndpointGroup.SocketAddress": {
          "Documentation": "http://docs.aws.amazon.com/AWSCloudFormation/latest/UserGuide/aws-properties-groundstation-dataflowendpointgroup-socketaddress.html",
          "Fixed": false,
          "Regions": [
            "ap-southeast-2",
            "eu-north-1",
            "eu-west-1",
            "me-south-1",
            "us-east-2",
            "us-west-2"
          ],
          "Since": "15.1.0"
        },
        "AWS::GroundStation::MissionProfile.DataflowEdge": {
          "Documentation": "http://docs.aws.amazon.com/AWSCloudFormation/latest/UserGuide/aws-properties-groundstation-missionprofile-dataflowedge.html",
          "Fixed": false,
          "Regions": [
            "ap-southeast-2",
            "eu-north-1",
            "eu-west-1",
            "me-south-1",
            "us-east-2",
            "us-west-2"
          ],
          "Since": "15.1.0"
        },
        "AWS::SSM::Association.ParameterValues": {
          "Documentation": "http://docs.aws.amazon.com/AWSCloudFormation/latest/UserGuide/aws-properties-ssm-association-parametervalues.html",
          "Fixed": false,
          "Regions": [
            "af-south-1",
            "ap-northeast-3",
            "eu-south-1"
          ],
          "Since": "15.1.0"
        }
      },
      "ResourceTypes": {
        "AWS::GroundStation::Config": {
          "Documentation": "http://docs.aws.amazon.com/AWSCloudFormation/latest/UserGuide/aws-resource-groundstation-config.html",
          "Fixed": false,
          "Regions": [
            "ap-southeast-2",
            "eu-north-1",
            "eu-west-1",
            "me-south-1",
            "us-east-2",
            "us-west-2"
          ],
          "Since": "15.1.0"
        },
        "AWS::GroundStation::DataflowEndpointGroup": {
          "Documentation": "http://docs.aws.amazon.com/AWSCloudFormation/latest/UserGuide/aws-resource-groundstation-dataflowendpointgroup.html",
          "Fixed": false,
          "Regions": [
            "ap-southeast-2",
            "eu-north-1",
            "eu-west-1",
            "me-south-1",
            "us-east-2",
            "us-west-2"
          ],
          "Since": "15.1.0"
        },
        "AWS::GroundStation::MissionProfile": {
          "Documentation": "http://docs.aws.amazon.com/AWSCloudFormation/latest/UserGuide/aws-resource-groundstation-missionprofile.html",
          "Fixed": false,
          "Regions": [
            "ap-southeast-2",
            "eu-north-1",
            "eu-west-1",
            "me-south-1",
            "us-east-2",
            "us-west-2"
          ],
          "Since": "15.1.0"
        }
      },
      "Total": {
        "Change": [
          0,
          4
        ],
        "Value": 10
      }
    }
  },
  "15.3.0": {
    "PropertyTypes": {
      "AWS::ApiGatewayV2::Integration.TlsConfig": {
        "AllRegions": false,
        "Documentation": "http://docs.aws.amazon.com/AWSCloudFormation/latest/UserGuide/aws-properties-apigatewayv2-integration-tlsconfig.html",
        "Expanded": [
          "us-gov-east-1"
        ],
        "Reduced": [],
        "Type": "Existing"
      },
      "AWS::Budgets::Budget.BudgetData": {
        "AllRegions": false,
        "Documentation": "http://docs.aws.amazon.com/AWSCloudFormation/latest/UserGuide/aws-properties-budgets-budget-budgetdata.html",
        "Expanded": [
          "cn-northwest-1",
          "cn-north-1"
        ],
        "Reduced": [],
        "Type": "Existing"
      },
      "AWS::Budgets::Budget.CostTypes": {
        "AllRegions": false,
        "Documentation": "http://docs.aws.amazon.com/AWSCloudFormation/latest/UserGuide/aws-properties-budgets-budget-costtypes.html",
        "Expanded": [
          "cn-northwest-1",
          "cn-north-1"
        ],
        "Reduced": [],
        "Type": "Existing"
      },
      "AWS::Budgets::Budget.Notification": {
        "AllRegions": false,
        "Documentation": "http://docs.aws.amazon.com/AWSCloudFormation/latest/UserGuide/aws-properties-budgets-budget-notification.html",
        "Expanded": [
          "cn-northwest-1",
          "cn-north-1"
        ],
        "Reduced": [],
        "Type": "Existing"
      },
      "AWS::Budgets::Budget.NotificationWithSubscribers": {
        "AllRegions": false,
        "Documentation": "http://docs.aws.amazon.com/AWSCloudFormation/latest/UserGuide/aws-properties-budgets-budget-notificationwithsubscribers.html",
        "Expanded": [
          "cn-northwest-1",
          "cn-north-1"
        ],
        "Reduced": [],
        "Type": "Existing"
      },
      "AWS::Budgets::Budget.Spend": {
        "AllRegions": false,
        "Documentation": "http://docs.aws.amazon.com/AWSCloudFormation/latest/UserGuide/aws-properties-budgets-budget-spend.html",
        "Expanded": [
          "cn-northwest-1",
          "cn-north-1"
        ],
        "Reduced": [],
        "Type": "Existing"
      },
      "AWS::Budgets::Budget.Subscriber": {
        "AllRegions": false,
        "Documentation": "http://docs.aws.amazon.com/AWSCloudFormation/latest/UserGuide/aws-properties-budgets-budget-subscriber.html",
        "Expanded": [
          "cn-northwest-1",
          "cn-north-1"
        ],
        "Reduced": [],
        "Type": "Existing"
      },
      "AWS::Budgets::Budget.TimePeriod": {
        "AllRegions": false,
        "Documentation": "http://docs.aws.amazon.com/AWSCloudFormation/latest/UserGuide/aws-properties-budgets-budget-timeperiod.html",
        "Expanded": [
          "cn-northwest-1",
          "cn-north-1"
        ],
        "Reduced": [],
        "Type": "Existing"
      },
      "AWS::EC2::LocalGatewayRouteTableVPCAssociation.Tags": {
        "AllRegions": false,
        "Documentation": "http://docs.aws.amazon.com/AWSCloudFormation/latest/UserGuide/aws-properties-ec2-localgatewayroutetablevpcassociation-tags.html",
        "Expanded": [
          "us-gov-east-1",
          "us-gov-west-1"
        ],
        "Reduced": [],
        "Type": "Existing"
      },
      "AWS::ECS::CapacityProvider.AutoScalingGroupProvider": {
        "AllRegions": false,
        "Documentation": "http://docs.aws.amazon.com/AWSCloudFormation/latest/UserGuide/aws-properties-ecs-capacityprovider-autoscalinggroupprovider.html",
        "Regions": [
          "ap-east-1",
          "ap-northeast-1",
          "ap-northeast-2",
          "ap-south-1",
          "ap-southeast-1",
          "ap-southeast-2",
          "ca-central-1",
          "cn-north-1",
          "cn-northwest-1",
          "eu-central-1",
          "eu-north-1",
          "eu-west-1",
          "eu-west-2",
          "eu-west-3",
          "me-south-1",
          "sa-east-1",
          "us-east-1",
          "us-east-2",
          "us-gov-east-1",
          "us-gov-west-1",
          "us-west-1",
          "us-west-2"
        ],
        "Type": "New"
      },
      "AWS::ECS::CapacityProvider.ManagedScaling": {
        "AllRegions": false,
        "Documentation": "http://docs.aws.amazon.com/AWSCloudFormation/latest/UserGuide/aws-properties-ecs-capacityprovider-managedscaling.html",
        "Regions": [
          "ap-east-1",
          "ap-northeast-1",
          "ap-northeast-2",
          "ap-south-1",
          "ap-southeast-1",
          "ap-southeast-2",
          "ca-central-1",
          "cn-north-1",
          "cn-northwest-1",
          "eu-central-1",
          "eu-north-1",
          "eu-west-1",
          "eu-west-2",
          "eu-west-3",
          "me-south-1",
          "sa-east-1",
          "us-east-1",
          "us-east-2",
          "us-gov-east-1",
          "us-gov-west-1",
          "us-west-1",
          "us-west-2"
        ],
        "Type": "New"
      },
      "AWS::ECS::Cluster.CapacityProviderStrategyItem": {
        "AllRegions": false,
        "Documentation": "http://docs.aws.amazon.com/AWSCloudFormation/latest/UserGuide/aws-properties-ecs-cluster-capacityproviderstrategyitem.html",
        "Regions": [
          "ap-east-1",
          "ap-northeast-1",
          "ap-northeast-2",
          "ap-south-1",
          "ap-southeast-1",
          "ap-southeast-2",
          "ca-central-1",
          "cn-north-1",
          "cn-northwest-1",
          "eu-central-1",
          "eu-north-1",
          "eu-west-1",
          "eu-west-2",
          "eu-west-3",
          "me-south-1",
          "sa-east-1",
          "us-east-1",
          "us-east-2",
          "us-gov-east-1",
          "us-gov-west-1",
          "us-west-1",
          "us-west-2"
        ],
        "Type": "New"
      },
      "AWS::Events::EventBusPolicy.Condition": {
        "AllRegions": false,
        "Documentation": "http://docs.aws.amazon.com/AWSCloudFormation/latest/UserGuide/aws-properties-events-eventbuspolicy-condition.html",
        "Expanded": [
          "me-south-1",
          "af-south-1",
          "eu-south-1"
        ],
        "Reduced": [],
        "Type": "Existing"
      },
      "AWS::Glue::MLTransform.FindMatchesParameters": {
        "AllRegions": false,
        "Documentation": "http://docs.aws.amazon.com/AWSCloudFormation/latest/UserGuide/aws-properties-glue-mltransform-transformparameters-findmatchesparameters.html",
        "Expanded": [
          "sa-east-1"
        ],
        "Reduced": [],
        "Type": "Existing"
      },
      "AWS::Glue::MLTransform.GlueTables": {
        "AllRegions": false,
        "Documentation": "http://docs.aws.amazon.com/AWSCloudFormation/latest/UserGuide/aws-properties-glue-mltransform-inputrecordtables-gluetables.html",
        "Expanded": [
          "sa-east-1"
        ],
        "Reduced": [],
        "Type": "Existing"
      },
      "AWS::Glue::MLTransform.InputRecordTables": {
        "AllRegions": false,
        "Documentation": "http://docs.aws.amazon.com/AWSCloudFormation/latest/UserGuide/aws-properties-glue-mltransform-inputrecordtables.html",
        "Expanded": [
          "sa-east-1"
        ],
        "Reduced": [],
        "Type": "Existing"
      },
      "AWS::Glue::MLTransform.TransformParameters": {
        "AllRegions": false,
        "Documentation": "http://docs.aws.amazon.com/AWSCloudFormation/latest/UserGuide/aws-properties-glue-mltransform-transformparameters.html",
        "Expanded": [
          "sa-east-1"
        ],
        "Reduced": [],
        "Type": "Existing"
      },
      "AWS::ManagedBlockchain::Member.ApprovalThresholdPolicy": {
        "AllRegions": false,
        "Documentation": "http://docs.aws.amazon.com/AWSCloudFormation/latest/UserGuide/aws-properties-managedblockchain-member-approvalthresholdpolicy.html",
        "Expanded": [
          "eu-central-1",
          "ap-northeast-2",
          "us-east-2",
          "us-west-2",
          "ap-northeast-1",
          "eu-west-1",
          "ap-southeast-1"
        ],
        "Reduced": [],
        "Type": "Existing"
      },
      "AWS::ManagedBlockchain::Member.MemberConfiguration": {
        "AllRegions": false,
        "Documentation": "http://docs.aws.amazon.com/AWSCloudFormation/latest/UserGuide/aws-properties-managedblockchain-member-memberconfiguration.html",
        "Expanded": [
          "eu-central-1",
          "ap-northeast-2",
          "us-east-2",
          "us-west-2",
          "ap-northeast-1",
          "eu-west-1",
          "ap-southeast-1"
        ],
        "Reduced": [],
        "Type": "Existing"
      },
      "AWS::ManagedBlockchain::Member.MemberFabricConfiguration": {
        "AllRegions": false,
        "Documentation": "http://docs.aws.amazon.com/AWSCloudFormation/latest/UserGuide/aws-properties-managedblockchain-member-memberfabricconfiguration.html",
        "Expanded": [
          "eu-central-1",
          "ap-northeast-2",
          "us-east-2",
          "us-west-2",
          "ap-northeast-1",
          "eu-west-1",
          "ap-southeast-1"
        ],
        "Reduced": [],
        "Type": "Existing"
      },
      "AWS::ManagedBlockchain::Member.MemberFrameworkConfiguration": {
        "AllRegions": false,
        "Documentation": "http://docs.aws.amazon.com/AWSCloudFormation/latest/UserGuide/aws-properties-managedblockchain-member-memberframeworkconfiguration.html",
        "Expanded": [
          "eu-central-1",
          "ap-northeast-2",
          "us-east-2",
          "us-west-2",
          "ap-northeast-1",
          "eu-west-1",
          "ap-southeast-1"
        ],
        "Reduced": [],
        "Type": "Existing"
      },
      "AWS::ManagedBlockchain::Member.NetworkConfiguration": {
        "AllRegions": false,
        "Documentation": "http://docs.aws.amazon.com/AWSCloudFormation/latest/UserGuide/aws-properties-managedblockchain-member-networkconfiguration.html",
        "Expanded": [
          "eu-central-1",
          "ap-northeast-2",
          "us-east-2",
          "us-west-2",
          "ap-northeast-1",
          "eu-west-1",
          "ap-southeast-1"
        ],
        "Reduced": [],
        "Type": "Existing"
      },
      "AWS::ManagedBlockchain::Member.NetworkFabricConfiguration": {
        "AllRegions": false,
        "Documentation": "http://docs.aws.amazon.com/AWSCloudFormation/latest/UserGuide/aws-properties-managedblockchain-member-networkfabricconfiguration.html",
        "Expanded": [
          "eu-central-1",
          "ap-northeast-2",
          "us-east-2",
          "us-west-2",
          "ap-northeast-1",
          "eu-west-1",
          "ap-southeast-1"
        ],
        "Reduced": [],
        "Type": "Existing"
      },
      "AWS::ManagedBlockchain::Member.NetworkFrameworkConfiguration": {
        "AllRegions": false,
        "Documentation": "http://docs.aws.amazon.com/AWSCloudFormation/latest/UserGuide/aws-properties-managedblockchain-member-networkframeworkconfiguration.html",
        "Expanded": [
          "eu-central-1",
          "ap-northeast-2",
          "us-east-2",
          "us-west-2",
          "ap-northeast-1",
          "eu-west-1",
          "ap-southeast-1"
        ],
        "Reduced": [],
        "Type": "Existing"
      },
      "AWS::ManagedBlockchain::Member.VotingPolicy": {
        "AllRegions": false,
        "Documentation": "http://docs.aws.amazon.com/AWSCloudFormation/latest/UserGuide/aws-properties-managedblockchain-member-votingpolicy.html",
        "Expanded": [
          "eu-central-1",
          "ap-northeast-2",
          "us-east-2",
          "us-west-2",
          "ap-northeast-1",
          "eu-west-1",
          "ap-southeast-1"
        ],
        "Reduced": [],
        "Type": "Existing"
      },
      "AWS::ManagedBlockchain::Node.NodeConfiguration": {
        "AllRegions": false,
        "Documentation": "http://docs.aws.amazon.com/AWSCloudFormation/latest/UserGuide/aws-properties-managedblockchain-node-nodeconfiguration.html",
        "Expanded": [
          "eu-central-1",
          "ap-northeast-2",
          "us-east-2",
          "us-west-2",
          "ap-northeast-1",
          "eu-west-1",
          "ap-southeast-1"
        ],
        "Reduced": [],
        "Type": "Existing"
      }
    },
    "ResourceSpecificationVersionOld": "15.2.0",
    "ResourceTypes": {
      "AWS::AppConfig::HostedConfigurationVersion": {
        "AllRegions": false,
        "Documentation": "http://docs.aws.amazon.com/AWSCloudFormation/latest/UserGuide/aws-resource-appconfig-hostedconfigurationversion.html",
        "Regions": [
          "ap-northeast-1",
          "ap-northeast-2",
          "ap-south-1",
          "ap-southeast-1",
          "ap-southeast-2",
          "ca-central-1",
          "eu-central-1",
          "eu-north-1",
          "eu-west-1",
          "eu-west-2",
          "eu-west-3",
          "me-south-1",
          "sa-east-1",
          "us-east-1",
          "us-east-2",
          "us-west-1",
          "us-west-2"
        ],
        "Type": "New"
      },
      "AWS::Budgets::Budget": {
        "AllRegions": false,
        "Documentation": "http://docs.aws.amazon.com/AWSCloudFormation/latest/UserGuide/aws-resource-budgets-budget.html",
        "Expanded": [
          "cn-northwest-1",
          "cn-north-1"
        ],
        "Reduced": [],
        "Type": "Existing"
      },
      "AWS::EC2::LocalGatewayRoute": {
        "AllRegions": false,
        "Documentation": "http://docs.aws.amazon.com/AWSCloudFormation/latest/UserGuide/aws-resource-ec2-localgatewayroute.html",
        "Expanded": [
          "us-gov-east-1",
          "us-gov-west-1"
        ],
        "Reduced": [],
        "Type": "Existing"
      },
      "AWS::EC2::LocalGatewayRouteTableVPCAssociation": {
        "AllRegions": false,
        "Documentation": "http://docs.aws.amazon.com/AWSCloudFormation/latest/UserGuide/aws-resource-ec2-localgatewayroutetablevpcassociation.html",
        "Expanded": [
          "us-gov-east-1",
          "us-gov-west-1"
        ],
        "Reduced": [],
        "Type": "Existing"
      },
      "AWS::ECS::CapacityProvider": {
        "AllRegions": false,
        "Documentation": "http://docs.aws.amazon.com/AWSCloudFormation/latest/UserGuide/aws-resource-ecs-capacityprovider.html",
        "Regions": [
          "ap-east-1",
          "ap-northeast-1",
          "ap-northeast-2",
          "ap-south-1",
          "ap-southeast-1",
          "ap-southeast-2",
          "ca-central-1",
          "cn-north-1",
          "cn-northwest-1",
          "eu-central-1",
          "eu-north-1",
          "eu-west-1",
          "eu-west-2",
          "eu-west-3",
          "me-south-1",
          "sa-east-1",
          "us-east-1",
          "us-east-2",
          "us-gov-east-1",
          "us-gov-west-1",
          "us-west-1",
          "us-west-2"
        ],
        "Type": "New"
      },
      "AWS::Events::EventBus": {
        "AllRegions": false,
        "Documentation": "http://docs.aws.amazon.com/AWSCloudFormation/latest/UserGuide/aws-resource-events-eventbus.html",
        "Expanded": [
          "me-south-1",
          "af-south-1",
          "eu-south-1"
        ],
        "Reduced": [],
        "Type": "Existing"
      },
      "AWS::Events::EventBusPolicy": {
        "AllRegions": false,
        "Documentation": "http://docs.aws.amazon.com/AWSCloudFormation/latest/UserGuide/aws-resource-events-eventbuspolicy.html",
        "Expanded": [
          "me-south-1",
          "af-south-1",
          "eu-south-1"
        ],
        "Reduced": [],
        "Type": "Existing"
      },
      "AWS::Glue::MLTransform": {
        "AllRegions": false,
        "Documentation": "http://docs.aws.amazon.com/AWSCloudFormation/latest/UserGuide/aws-resource-glue-mltransform.html",
        "Expanded": [
          "sa-east-1"
        ],
        "Reduced": [],
        "Type": "Existing"
      },
      "AWS::ManagedBlockchain::Member": {
        "AllRegions": false,
        "Documentation": "http://docs.aws.amazon.com/AWSCloudFormation/latest/UserGuide/aws-resource-managedblockchain-member.html",
        "Expanded": [
          "eu-central-1",
          "ap-northeast-2",
          "us-east-2",
          "us-west-2",
          "ap-northeast-1",
          "eu-west-1",
          "ap-southeast-1"
        ],
        "Reduced": [],
        "Type": "Existing"
      },
      "AWS::ManagedBlockchain::Node": {
        "AllRegions": false,
        "Documentation": "http://docs.aws.amazon.com/AWSCloudFormation/latest/UserGuide/aws-resource-managedblockchain-node.html",
        "Expanded": [
          "eu-central-1",
          "ap-northeast-2",
          "us-east-2",
          "us-west-2",
          "ap-northeast-1",
          "eu-west-1",
          "ap-southeast-1"
        ],
        "Reduced": [],
        "Type": "Existing"
      }
    },
    "Totals": {
      "TotalPropertyTypes": {
        "Change": [
          3
        ],
        "Value": 1375
      },
      "TotalPropertyTypesSupportedGlobally": {
        "Change": [
          0
        ],
        "Value": 488
      },
      "TotalResourceTypes": {
        "Change": [
          2
        ],
        "Value": 544
      },
      "TotalResourceTypesSupportedGlobally": {
        "Change": [
          0
        ],
        "Value": 187
      }
    },
    "TypesNotInUSEAST1": {
      "PropertyTypes": {
        "AWS::ECS::Cluster.ClusterSetting": {
          "Documentation": "http://docs.aws.amazon.com/AWSCloudFormation/latest/UserGuide/aws-properties-ecs-cluster-clustersetting.html",
          "Fixed": false,
          "Regions": [
            "af-south-1",
            "ap-northeast-3",
            "eu-south-1"
          ],
          "Since": "15.2.0"
        },
        "AWS::GroundStation::DataflowEndpointGroup.DataflowEndpoint": {
          "Documentation": "http://docs.aws.amazon.com/AWSCloudFormation/latest/UserGuide/aws-properties-groundstation-dataflowendpointgroup-dataflowendpoint.html",
          "Fixed": false,
          "Regions": [
            "ap-southeast-2",
            "eu-north-1",
            "eu-west-1",
            "me-south-1",
            "us-east-2",
            "us-west-2"
          ],
          "Since": "15.2.0"
        },
        "AWS::GroundStation::DataflowEndpointGroup.EndpointDetails": {
          "Documentation": "http://docs.aws.amazon.com/AWSCloudFormation/latest/UserGuide/aws-properties-groundstation-dataflowendpointgroup-endpointdetails.html",
          "Fixed": false,
          "Regions": [
            "ap-southeast-2",
            "eu-north-1",
            "eu-west-1",
            "me-south-1",
            "us-east-2",
            "us-west-2"
          ],
          "Since": "15.2.0"
        },
        "AWS::GroundStation::DataflowEndpointGroup.SecurityDetails": {
          "Documentation": "http://docs.aws.amazon.com/AWSCloudFormation/latest/UserGuide/aws-properties-groundstation-dataflowendpointgroup-securitydetails.html",
          "Fixed": false,
          "Regions": [
            "ap-southeast-2",
            "eu-north-1",
            "eu-west-1",
            "me-south-1",
            "us-east-2",
            "us-west-2"
          ],
          "Since": "15.2.0"
        },
        "AWS::GroundStation::DataflowEndpointGroup.SocketAddress": {
          "Documentation": "http://docs.aws.amazon.com/AWSCloudFormation/latest/UserGuide/aws-properties-groundstation-dataflowendpointgroup-socketaddress.html",
          "Fixed": false,
          "Regions": [
            "ap-southeast-2",
            "eu-north-1",
            "eu-west-1",
            "me-south-1",
            "us-east-2",
            "us-west-2"
          ],
          "Since": "15.2.0"
        },
        "AWS::GroundStation::MissionProfile.DataflowEdge": {
          "Documentation": "http://docs.aws.amazon.com/AWSCloudFormation/latest/UserGuide/aws-properties-groundstation-missionprofile-dataflowedge.html",
          "Fixed": false,
          "Regions": [
            "ap-southeast-2",
            "eu-north-1",
            "eu-west-1",
            "me-south-1",
            "us-east-2",
            "us-west-2"
          ],
          "Since": "15.2.0"
        },
        "AWS::SSM::Association.ParameterValues": {
          "Documentation": "http://docs.aws.amazon.com/AWSCloudFormation/latest/UserGuide/aws-properties-ssm-association-parametervalues.html",
          "Fixed": false,
          "Regions": [
            "af-south-1",
            "ap-northeast-3",
            "eu-south-1"
          ],
          "Since": "15.2.0"
        }
      },
      "ResourceTypes": {
        "AWS::GroundStation::Config": {
          "Documentation": "http://docs.aws.amazon.com/AWSCloudFormation/latest/UserGuide/aws-resource-groundstation-config.html",
          "Fixed": false,
          "Regions": [
            "ap-southeast-2",
            "eu-north-1",
            "eu-west-1",
            "me-south-1",
            "us-east-2",
            "us-west-2"
          ],
          "Since": "15.2.0"
        },
        "AWS::GroundStation::DataflowEndpointGroup": {
          "Documentation": "http://docs.aws.amazon.com/AWSCloudFormation/latest/UserGuide/aws-resource-groundstation-dataflowendpointgroup.html",
          "Fixed": false,
          "Regions": [
            "ap-southeast-2",
            "eu-north-1",
            "eu-west-1",
            "me-south-1",
            "us-east-2",
            "us-west-2"
          ],
          "Since": "15.2.0"
        },
        "AWS::GroundStation::MissionProfile": {
          "Documentation": "http://docs.aws.amazon.com/AWSCloudFormation/latest/UserGuide/aws-resource-groundstation-missionprofile.html",
          "Fixed": false,
          "Regions": [
            "ap-southeast-2",
            "eu-north-1",
            "eu-west-1",
            "me-south-1",
            "us-east-2",
            "us-west-2"
          ],
          "Since": "15.2.0"
        }
      },
      "Total": {
        "Change": [
          0,
          0
        ],
        "Value": 10
      }
    }
  }
}