{
  "64.0.0": {
    "PropertyTypes": {
      "AWS::AppStream::DirectoryConfig.ServiceAccountCredentials": {
        "AllRegions": false,
        "Documentation": "http://docs.aws.amazon.com/AWSCloudFormation/latest/UserGuide/aws-properties-appstream-directoryconfig-serviceaccountcredentials.html",
        "Expanded": [
          "ca-central-1"
        ],
        "Reduced": [],
        "Type": "Existing"
      },
      "AWS::AppStream::Fleet.ComputeCapacity": {
        "AllRegions": false,
        "Documentation": "http://docs.aws.amazon.com/AWSCloudFormation/latest/UserGuide/aws-properties-appstream-fleet-computecapacity.html",
        "Expanded": [
          "ca-central-1"
        ],
        "Reduced": [],
        "Type": "Existing"
      },
      "AWS::AppStream::Fleet.DomainJoinInfo": {
        "AllRegions": false,
        "Documentation": "http://docs.aws.amazon.com/AWSCloudFormation/latest/UserGuide/aws-properties-appstream-fleet-domainjoininfo.html",
        "Expanded": [
          "ca-central-1"
        ],
        "Reduced": [],
        "Type": "Existing"
      },
      "AWS::AppStream::Fleet.VpcConfig": {
        "AllRegions": false,
        "Documentation": "http://docs.aws.amazon.com/AWSCloudFormation/latest/UserGuide/aws-properties-appstream-fleet-vpcconfig.html",
        "Expanded": [
          "ca-central-1"
        ],
        "Reduced": [],
        "Type": "Existing"
      },
      "AWS::AppStream::ImageBuilder.AccessEndpoint": {
        "AllRegions": false,
        "Documentation": "http://docs.aws.amazon.com/AWSCloudFormation/latest/UserGuide/aws-properties-appstream-imagebuilder-accessendpoint.html",
        "Expanded": [
          "ca-central-1"
        ],
        "Reduced": [],
        "Type": "Existing"
      },
      "AWS::AppStream::ImageBuilder.DomainJoinInfo": {
        "AllRegions": false,
        "Documentation": "http://docs.aws.amazon.com/AWSCloudFormation/latest/UserGuide/aws-properties-appstream-imagebuilder-domainjoininfo.html",
        "Expanded": [
          "ca-central-1"
        ],
        "Reduced": [],
        "Type": "Existing"
      },
      "AWS::AppStream::ImageBuilder.VpcConfig": {
        "AllRegions": false,
        "Documentation": "http://docs.aws.amazon.com/AWSCloudFormation/latest/UserGuide/aws-properties-appstream-imagebuilder-vpcconfig.html",
        "Expanded": [
          "ca-central-1"
        ],
        "Reduced": [],
        "Type": "Existing"
      },
      "AWS::AppStream::Stack.AccessEndpoint": {
        "AllRegions": false,
        "Documentation": "http://docs.aws.amazon.com/AWSCloudFormation/latest/UserGuide/aws-properties-appstream-stack-accessendpoint.html",
        "Expanded": [
          "ca-central-1"
        ],
        "Reduced": [],
        "Type": "Existing"
      },
      "AWS::AppStream::Stack.ApplicationSettings": {
        "AllRegions": false,
        "Documentation": "http://docs.aws.amazon.com/AWSCloudFormation/latest/UserGuide/aws-properties-appstream-stack-applicationsettings.html",
        "Expanded": [
          "ca-central-1"
        ],
        "Reduced": [],
        "Type": "Existing"
      },
      "AWS::AppStream::Stack.StorageConnector": {
        "AllRegions": false,
        "Documentation": "http://docs.aws.amazon.com/AWSCloudFormation/latest/UserGuide/aws-properties-appstream-stack-storageconnector.html",
        "Expanded": [
          "ca-central-1"
        ],
        "Reduced": [],
        "Type": "Existing"
      },
      "AWS::AppStream::Stack.UserSetting": {
        "AllRegions": false,
        "Documentation": "http://docs.aws.amazon.com/AWSCloudFormation/latest/UserGuide/aws-properties-appstream-stack-usersetting.html",
        "Expanded": [
          "ca-central-1"
        ],
        "Reduced": [],
        "Type": "Existing"
      },
      "AWS::EC2::TransitGatewayConnect.TransitGatewayConnectOptions": {
        "AllRegions": false,
        "Documentation": "http://docs.aws.amazon.com/AWSCloudFormation/latest/UserGuide/aws-properties-ec2-transitgatewayconnect-transitgatewayconnectoptions.html",
        "Expanded": [
          "eu-west-2"
        ],
        "Reduced": [],
        "Type": "Existing"
      },
      "AWS::Events::Endpoint.EndpointEventBus": {
        "AllRegions": false,
        "Documentation": "http://docs.aws.amazon.com/AWSCloudFormation/latest/UserGuide/aws-properties-events-endpoint-endpointeventbus.html",
        "Expanded": [],
        "Reduced": [
          "us-east-2",
          "ap-southeast-1",
          "us-west-1",
          "ap-southeast-2",
          "us-west-2",
          "ap-northeast-2",
          "ca-central-1",
          "us-east-1",
          "ap-south-1",
          "ap-northeast-3",
          "eu-north-1",
          "eu-west-1",
          "eu-west-2",
          "eu-west-3",
          "sa-east-1",
          "ap-northeast-1"
        ],
        "Type": "Existing"
      },
      "AWS::Events::Endpoint.FailoverConfig": {
        "AllRegions": false,
        "Documentation": "http://docs.aws.amazon.com/AWSCloudFormation/latest/UserGuide/aws-properties-events-endpoint-failoverconfig.html",
        "Expanded": [],
        "Reduced": [
          "us-east-2",
          "ap-southeast-1",
          "us-west-1",
          "ap-southeast-2",
          "us-west-2",
          "ap-northeast-2",
          "ca-central-1",
          "us-east-1",
          "ap-south-1",
          "ap-northeast-3",
          "eu-north-1",
          "eu-west-1",
          "eu-west-2",
          "eu-west-3",
          "sa-east-1",
          "ap-northeast-1"
        ],
        "Type": "Existing"
      },
      "AWS::Events::Endpoint.Primary": {
        "AllRegions": false,
        "Documentation": "http://docs.aws.amazon.com/AWSCloudFormation/latest/UserGuide/aws-properties-events-endpoint-primary.html",
        "Expanded": [],
        "Reduced": [
          "us-east-2",
          "ap-southeast-1",
          "us-west-1",
          "ap-southeast-2",
          "us-west-2",
          "ap-northeast-2",
          "ca-central-1",
          "us-east-1",
          "ap-south-1",
          "ap-northeast-3",
          "eu-north-1",
          "eu-west-1",
          "eu-west-2",
          "eu-west-3",
          "sa-east-1",
          "ap-northeast-1"
        ],
        "Type": "Existing"
      },
      "AWS::Events::Endpoint.ReplicationConfig": {
        "AllRegions": false,
        "Documentation": "http://docs.aws.amazon.com/AWSCloudFormation/latest/UserGuide/aws-properties-events-endpoint-replicationconfig.html",
        "Expanded": [],
        "Reduced": [
          "us-east-2",
          "ap-southeast-1",
          "us-west-1",
          "ap-southeast-2",
          "us-west-2",
          "ap-northeast-2",
          "ca-central-1",
          "us-east-1",
          "ap-south-1",
          "ap-northeast-3",
          "eu-north-1",
          "eu-west-1",
          "eu-west-2",
          "eu-west-3",
          "sa-east-1",
          "ap-northeast-1"
        ],
        "Type": "Existing"
      },
      "AWS::Events::Endpoint.RoutingConfig": {
        "AllRegions": false,
        "Documentation": "http://docs.aws.amazon.com/AWSCloudFormation/latest/UserGuide/aws-properties-events-endpoint-routingconfig.html",
        "Expanded": [],
        "Reduced": [
          "us-east-2",
          "ap-southeast-1",
          "us-west-1",
          "ap-southeast-2",
          "us-west-2",
          "ap-northeast-2",
          "ca-central-1",
          "us-east-1",
          "ap-south-1",
          "ap-northeast-3",
          "eu-north-1",
          "eu-west-1",
          "eu-west-2",
          "eu-west-3",
          "sa-east-1",
          "ap-northeast-1"
        ],
        "Type": "Existing"
      },
      "AWS::Events::Endpoint.Secondary": {
        "AllRegions": false,
        "Documentation": "http://docs.aws.amazon.com/AWSCloudFormation/latest/UserGuide/aws-properties-events-endpoint-secondary.html",
        "Expanded": [],
        "Reduced": [
          "us-east-2",
          "ap-southeast-1",
          "us-west-1",
          "ap-southeast-2",
          "us-west-2",
          "ap-northeast-2",
          "ca-central-1",
          "us-east-1",
          "ap-south-1",
          "ap-northeast-3",
          "eu-north-1",
          "eu-west-1",
          "eu-west-2",
          "eu-west-3",
          "sa-east-1",
          "ap-northeast-1"
        ],
        "Type": "Existing"
      },
      "AWS::SageMaker::Domain.DomainSettings": {
        "AllRegions": false,
        "Documentation": "http://docs.aws.amazon.com/AWSCloudFormation/latest/UserGuide/aws-properties-sagemaker-domain-domainsettings.html",
        "Expanded": [
          "me-south-1",
          "us-east-2",
          "ap-southeast-1",
          "us-west-1",
          "ap-southeast-2",
          "eu-south-1",
          "ap-northeast-2",
          "ca-central-1",
          "ap-east-1",
          "us-east-1",
          "ap-south-1",
          "cn-northwest-1",
          "eu-north-1",
          "af-south-1",
          "eu-west-1",
          "eu-west-2",
          "eu-west-3",
          "sa-east-1",
          "ap-northeast-1"
        ],
        "Reduced": [],
        "Type": "Existing"
      },
      "AWS::SageMaker::Domain.RStudioServerProAppSettings": {
        "AllRegions": false,
        "Documentation": "http://docs.aws.amazon.com/AWSCloudFormation/latest/UserGuide/aws-properties-sagemaker-domain-rstudioserverproappsettings.html",
        "Expanded": [
          "me-south-1",
          "us-east-2",
          "ap-southeast-1",
          "us-west-1",
          "ap-southeast-2",
          "eu-south-1",
          "ap-northeast-2",
          "ca-central-1",
          "ap-east-1",
          "us-east-1",
          "ap-south-1",
          "cn-northwest-1",
          "eu-north-1",
          "af-south-1",
          "eu-west-1",
          "eu-west-2",
          "eu-west-3",
          "sa-east-1",
          "ap-northeast-1"
        ],
        "Reduced": [],
        "Type": "Existing"
      },
      "AWS::SageMaker::Domain.RStudioServerProDomainSettings": {
        "AllRegions": false,
        "Documentation": "http://docs.aws.amazon.com/AWSCloudFormation/latest/UserGuide/aws-properties-sagemaker-domain-rstudioserverprodomainsettings.html",
        "Expanded": [
          "me-south-1",
          "us-east-2",
          "ap-southeast-1",
          "us-west-1",
          "ap-southeast-2",
          "eu-south-1",
          "ap-northeast-2",
          "ca-central-1",
          "ap-east-1",
          "us-east-1",
          "ap-south-1",
          "cn-northwest-1",
          "eu-north-1",
          "af-south-1",
          "eu-west-1",
          "eu-west-2",
          "eu-west-3",
          "sa-east-1",
          "ap-northeast-1"
        ],
        "Reduced": [],
        "Type": "Existing"
      },
      "AWS::SageMaker::UserProfile.RStudioServerProAppSettings": {
        "AllRegions": false,
        "Documentation": "http://docs.aws.amazon.com/AWSCloudFormation/latest/UserGuide/aws-properties-sagemaker-userprofile-rstudioserverproappsettings.html",
        "Expanded": [
          "me-south-1",
          "us-east-2",
          "ap-southeast-1",
          "us-west-1",
          "ap-southeast-2",
          "eu-south-1",
          "ap-northeast-2",
          "ca-central-1",
          "ap-east-1",
          "us-east-1",
          "ap-south-1",
          "eu-north-1",
          "af-south-1",
          "eu-west-1",
          "eu-west-2",
          "eu-west-3",
          "sa-east-1",
          "ap-northeast-1"
        ],
        "Reduced": [],
        "Type": "Existing"
      }
    },
    "ResourceSpecificationVersionOld": "63.0.0",
    "ResourceTypes": {
      "AWS::AppStream::DirectoryConfig": {
        "AllRegions": false,
        "Documentation": "http://docs.aws.amazon.com/AWSCloudFormation/latest/UserGuide/aws-resource-appstream-directoryconfig.html",
        "Expanded": [
          "ca-central-1"
        ],
        "Reduced": [],
        "Type": "Existing"
      },
      "AWS::AppStream::Fleet": {
        "AllRegions": false,
        "Documentation": "http://docs.aws.amazon.com/AWSCloudFormation/latest/UserGuide/aws-resource-appstream-fleet.html",
        "Expanded": [
          "ca-central-1"
        ],
        "Reduced": [],
        "Type": "Existing"
      },
      "AWS::AppStream::ImageBuilder": {
        "AllRegions": false,
        "Documentation": "http://docs.aws.amazon.com/AWSCloudFormation/latest/UserGuide/aws-resource-appstream-imagebuilder.html",
        "Expanded": [
          "ca-central-1"
        ],
        "Reduced": [],
        "Type": "Existing"
      },
      "AWS::AppStream::Stack": {
        "AllRegions": false,
        "Documentation": "http://docs.aws.amazon.com/AWSCloudFormation/latest/UserGuide/aws-resource-appstream-stack.html",
        "Expanded": [
          "ca-central-1"
        ],
        "Reduced": [],
        "Type": "Existing"
      },
      "AWS::AppStream::StackFleetAssociation": {
        "AllRegions": false,
        "Documentation": "http://docs.aws.amazon.com/AWSCloudFormation/latest/UserGuide/aws-resource-appstream-stackfleetassociation.html",
        "Expanded": [
          "ca-central-1"
        ],
        "Reduced": [],
        "Type": "Existing"
      },
      "AWS::AppStream::StackUserAssociation": {
        "AllRegions": false,
        "Documentation": "http://docs.aws.amazon.com/AWSCloudFormation/latest/UserGuide/aws-resource-appstream-stackuserassociation.html",
        "Expanded": [
          "ca-central-1"
        ],
        "Reduced": [],
        "Type": "Existing"
      },
      "AWS::AppStream::User": {
        "AllRegions": false,
        "Documentation": "http://docs.aws.amazon.com/AWSCloudFormation/latest/UserGuide/aws-resource-appstream-user.html",
        "Expanded": [
          "ca-central-1"
        ],
        "Reduced": [],
        "Type": "Existing"
      },
      "AWS::EC2::TransitGatewayConnect": {
        "AllRegions": false,
        "Documentation": "http://docs.aws.amazon.com/AWSCloudFormation/latest/UserGuide/aws-resource-ec2-transitgatewayconnect.html",
        "Expanded": [
          "eu-west-2"
        ],
        "Reduced": [],
        "Type": "Existing"
      },
      "AWS::Events::Endpoint": {
        "AllRegions": false,
        "Documentation": "http://docs.aws.amazon.com/AWSCloudFormation/latest/UserGuide/aws-resource-events-endpoint.html",
        "Expanded": [],
        "Reduced": [
          "us-east-2",
          "ap-southeast-1",
          "us-west-1",
          "ap-southeast-2",
          "us-west-2",
          "ap-northeast-2",
          "ca-central-1",
          "us-east-1",
          "ap-south-1",
          "ap-northeast-3",
          "eu-north-1",
          "eu-west-1",
          "eu-west-2",
          "eu-west-3",
          "sa-east-1",
          "ap-northeast-1"
        ],
        "Type": "Existing"
      },
      "AWS::KinesisVideo::SignalingChannel": {
        "AllRegions": false,
        "Documentation": "http://docs.aws.amazon.com/AWSCloudFormation/latest/UserGuide/aws-resource-kinesisvideo-signalingchannel.html",
        "Expanded": [
          "ap-south-1"
        ],
        "Reduced": [],
        "Type": "Existing"
      },
      "AWS::KinesisVideo::Stream": {
        "AllRegions": false,
        "Documentation": "http://docs.aws.amazon.com/AWSCloudFormation/latest/UserGuide/aws-resource-kinesisvideo-stream.html",
        "Expanded": [
          "ap-south-1"
        ],
        "Reduced": [],
        "Type": "Existing"
      }
    },
    "Totals": {
      "TotalPropertyTypes": {
        "Change": [
          0
        ],
        "Value": 3064
      },
      "TotalPropertyTypesSupportedGlobally": {
        "Change": [
          0
        ],
        "Value": 1079
      },
      "TotalResourceTypes": {
        "Change": [
          0
        ],
        "Value": 907
      },
      "TotalResourceTypesSupportedGlobally": {
        "Change": [
          0
        ],
        "Value": 339
      }
    },
    "TypesNotInUSEAST1": {
      "PropertyTypes": {
        "AWS::DeviceFarm::DevicePool.Rule": {
          "Documentation": "http://docs.aws.amazon.com/AWSCloudFormation/latest/UserGuide/aws-properties-devicefarm-devicepool-rule.html",
          "Fixed": false,
          "Regions": [
            "us-west-2"
          ],
          "Since": "63.0.0"
        },
        "AWS::DeviceFarm::TestGridProject.VpcConfig": {
          "Documentation": "http://docs.aws.amazon.com/AWSCloudFormation/latest/UserGuide/aws-properties-devicefarm-testgridproject-vpcconfig.html",
          "Fixed": false,
          "Regions": [
            "us-west-2"
          ],
          "Since": "63.0.0"
        },
        "AWS::EC2::Subnet.PrivateDnsNameOptionsOnLaunch": {
          "Documentation": "http://docs.aws.amazon.com/AWSCloudFormation/latest/UserGuide/aws-properties-ec2-subnet-privatednsnameoptionsonlaunch.html",
          "Fixed": false,
          "Regions": [
            "us-gov-east-1",
            "us-gov-west-1"
          ],
          "Since": "63.0.0"
        },
        "AWS::Events::Endpoint.EndpointEventBus": {
          "Documentation": "http://docs.aws.amazon.com/AWSCloudFormation/latest/UserGuide/aws-properties-events-endpoint-endpointeventbus.html",
          "Fixed": false,
          "Regions": [
            "eu-central-1"
          ],
          "Since": "63.0.0"
        },
        "AWS::Events::Endpoint.FailoverConfig": {
          "Documentation": "http://docs.aws.amazon.com/AWSCloudFormation/latest/UserGuide/aws-properties-events-endpoint-failoverconfig.html",
          "Fixed": false,
          "Regions": [
            "eu-central-1"
          ],
          "Since": "63.0.0"
        },
        "AWS::Events::Endpoint.Primary": {
          "Documentation": "http://docs.aws.amazon.com/AWSCloudFormation/latest/UserGuide/aws-properties-events-endpoint-primary.html",
          "Fixed": false,
          "Regions": [
            "eu-central-1"
          ],
          "Since": "63.0.0"
        },
        "AWS::Events::Endpoint.ReplicationConfig": {
          "Documentation": "http://docs.aws.amazon.com/AWSCloudFormation/latest/UserGuide/aws-properties-events-endpoint-replicationconfig.html",
          "Fixed": false,
          "Regions": [
            "eu-central-1"
          ],
          "Since": "63.0.0"
        },
        "AWS::Events::Endpoint.RoutingConfig": {
          "Documentation": "http://docs.aws.amazon.com/AWSCloudFormation/latest/UserGuide/aws-properties-events-endpoint-routingconfig.html",
          "Fixed": false,
          "Regions": [
            "eu-central-1"
          ],
          "Since": "63.0.0"
        },
        "AWS::Events::Endpoint.Secondary": {
          "Documentation": "http://docs.aws.amazon.com/AWSCloudFormation/latest/UserGuide/aws-properties-events-endpoint-secondary.html",
          "Fixed": false,
          "Regions": [
            "eu-central-1"
          ],
          "Since": "63.0.0"
        },
        "AWS::Route53::HealthCheck.AlarmIdentifier": {
          "Documentation": "http://docs.aws.amazon.com/AWSCloudFormation/latest/UserGuide/aws-properties-route53-healthcheck-alarmidentifier.html",
          "Fixed": false,
          "Regions": [
            "af-south-1",
            "cn-north-1",
            "cn-northwest-1",
            "eu-south-1",
            "us-gov-east-1",
            "us-gov-west-1"
          ],
          "Since": "63.0.0"
        },
        "AWS::Route53::HealthCheck.HealthCheckConfig": {
          "Documentation": "http://docs.aws.amazon.com/AWSCloudFormation/latest/UserGuide/aws-properties-route53-healthcheck-healthcheckconfig.html",
          "Fixed": false,
          "Regions": [
            "af-south-1",
            "cn-north-1",
            "cn-northwest-1",
            "eu-south-1",
            "us-gov-east-1",
            "us-gov-west-1"
          ],
          "Since": "63.0.0"
        }
      },
      "ResourceTypes": {
        "AWS::DeviceFarm::DevicePool": {
          "Documentation": "http://docs.aws.amazon.com/AWSCloudFormation/latest/UserGuide/aws-resource-devicefarm-devicepool.html",
          "Fixed": false,
          "Regions": [
            "us-west-2"
          ],
          "Since": "63.0.0"
        },
        "AWS::DeviceFarm::InstanceProfile": {
          "Documentation": "http://docs.aws.amazon.com/AWSCloudFormation/latest/UserGuide/aws-resource-devicefarm-instanceprofile.html",
          "Fixed": false,
          "Regions": [
            "us-west-2"
          ],
          "Since": "63.0.0"
        },
        "AWS::DeviceFarm::NetworkProfile": {
          "Documentation": "http://docs.aws.amazon.com/AWSCloudFormation/latest/UserGuide/aws-resource-devicefarm-networkprofile.html",
          "Fixed": false,
          "Regions": [
            "us-west-2"
          ],
          "Since": "63.0.0"
        },
        "AWS::DeviceFarm::Project": {
          "Documentation": "http://docs.aws.amazon.com/AWSCloudFormation/latest/UserGuide/aws-resource-devicefarm-project.html",
          "Fixed": false,
          "Regions": [
            "us-west-2"
          ],
          "Since": "63.0.0"
        },
        "AWS::DeviceFarm::TestGridProject": {
          "Documentation": "http://docs.aws.amazon.com/AWSCloudFormation/latest/UserGuide/aws-resource-devicefarm-testgridproject.html",
          "Fixed": false,
          "Regions": [
            "us-west-2"
          ],
          "Since": "63.0.0"
        },
        "AWS::DeviceFarm::VPCEConfiguration": {
          "Documentation": "http://docs.aws.amazon.com/AWSCloudFormation/latest/UserGuide/aws-resource-devicefarm-vpceconfiguration.html",
          "Fixed": false,
          "Regions": [
            "us-west-2"
          ],
          "Since": "63.0.0"
        },
        "AWS::Events::Endpoint": {
          "Documentation": "http://docs.aws.amazon.com/AWSCloudFormation/latest/UserGuide/aws-resource-events-endpoint.html",
          "Fixed": false,
          "Regions": [
            "eu-central-1"
          ],
          "Since": "63.0.0"
        }
      },
      "Total": {
        "Change": [
          0,
          4
        ],
        "Value": 18
      }
    }
  }
}